Utils/__init__.py
Utils/agreement_utils.py
Utils/confident_interval.py
Utils/logger.py
Utils/pretty_print.py
Utils/pretty_print_console.py
Utils/pretty_print_csv.py
Utils/pretty_print_html.py
iaa_eval-0.1.0.dist-info/METADATA
iaa_eval-0.1.0.dist-info/WHEEL
iaa_eval-0.1.0.dist-info/entry_points.txt
iaa_eval-0.1.0.dist-info/top_level.txt
iaa_eval-0.1.0.dist-info/RECORD
