Metadata-Version: 2.4
Name: iaa-eval
Version: 0.1.0
Summary: A Command-Line Tool for Inter-Annotator Agreement Evaluation
Home-page: https://github.com/Wameuh/AnnotationQuality
Author: Wameuh
Author-email: wameuh@gmail.com
Classifier: Development Status :: 3 - Alpha
Classifier: Intended Audience :: Science/Research
Classifier: License :: OSI Approved :: MIT License
Classifier: Operating System :: OS Independent
Classifier: Programming Language :: Python :: 3
Classifier: Programming Language :: Python :: 3.8
Classifier: Programming Language :: Python :: 3.9
Classifier: Programming Language :: Python :: 3.10
Classifier: Topic :: Scientific/Engineering :: Information Analysis
Requires-Python: >=3.8
Requires-Dist: matplotlib==3.10.1
Requires-Dist: numpy==2.2.4
Requires-Dist: pandas==2.2.3
Requires-Dist: scipy==1.15.2
Requires-Dist: tabulate==0.9.0
Dynamic: author
Dynamic: author-email
Dynamic: classifier
Dynamic: description
Dynamic: description-content-type
Dynamic: home-page
Dynamic: requires-dist
Dynamic: requires-python
Dynamic: summary
